{
    "country": "RO",
    "country_name": "Romania",
    "country_name_local": "România",
    "lang": "ro",
    "lang_dir": "ltr",
    "name": "Română",
    "date_numbers": "d.m.Y",
    "date_numbers_full_capitals": "DD.MM.YYYY",
    "date_words_without_day": "j F Y",
    "date_words_with_day": "l, j F Y",
    "date_birthday": "j F",
    "time_format": "H:i",
    "emoji_flag": "🇷🇴",
    "currency_code": "RON",
    "currency_symbol": "lei",
    "currency_symbol_local": "lei",
    "currency_name": "Romanian Leu",
    "currency_name_local": "Leu românesc"
}
